pathlesstaken/__init__.py
pathlesstaken/internationalstrings.py
pathlesstaken/names.py
pathlesstaken/pathlesstaken.py
pathlesstaken/ucd.py
pathlesstaken/version.py
pathlesstaken/i18n/__init__.py
pathlesstaken/i18n/internationalstrings.py
pathlesstaken-1.0.2rc1.dist-info/LICENSE
pathlesstaken-1.0.2rc1.dist-info/METADATA
pathlesstaken-1.0.2rc1.dist-info/WHEEL
pathlesstaken-1.0.2rc1.dist-info/entry_points.txt
pathlesstaken-1.0.2rc1.dist-info/top_level.txt
pathlesstaken-1.0.2rc1.dist-info/RECORD
