Metadata-Version: 2.1
Name: pathlesstaken
Version: 1.0.2rc1
Summary: Library and executable for identifying anomalous file path strings
Home-page: https://github.com/exponential-decay/pathlesstaken
Author: Ross Spencer
Author-email: all.along.the.watchtower2001+github@gmail.com
License: UNKNOWN
Project-URL: Part of demystify, https://github.com/exponential-decay/demystify
Project-URL: Bug Reports, https://github.com/exponential-decay/demystify/issues
Project-URL: Source, https://github.com/exponential-decay/pathlesstaken
Project-URL: Ko-Fi, https://ko-fi.com/beet_keeper
Keywords: digital-preservation,file-analysis,string-analysis,filename-analysis
Platform: UNKNOWN
Classifier: Development Status :: 5 - Production/Stable
Classifier: Intended Audience :: Developers
Classifier: Intended Audience :: Information Technology
Classifier: Intended Audience :: Other Audience
Classifier: Topic :: System :: Archiving
Classifier: License :: OSI Approved :: GNU General Public License v3 (GPLv3)
Classifier: Programming Language :: Python :: 3
Requires-Python: >=3.9, <4
